giotto_llm/__init__.py
giotto_llm/__main__.py
giotto_llm/bucket/__init__.py
giotto_llm/bucket/__main__.py
giotto_llm/bucket/deserialize.py
giotto_llm/bucket/get_synth_data.py
giotto_llm/bucket/serialize.py
giotto_llm/causal_lm/__init__.py
giotto_llm/causal_lm/models.py
giotto_llm/consts.py
giotto_llm/data.py
giotto_llm/finetuning/__init__.py
giotto_llm/finetuning/__main__.py
giotto_llm/finetuning/args.py
giotto_llm/finetuning/merge.py
giotto_llm/finetuning/pretraining.py
giotto_llm/finetuning/prune.py
giotto_llm/finetuning/save_base_model.py
giotto_llm/finetuning/utils.py
giotto_llm/generate_messages/__init__.py
giotto_llm/generate_messages/__main__.py
giotto_llm/generate_messages/messages_generator.py
giotto_llm/logs.py
giotto_llm/multimodal/molmo.py
giotto_llm/multimodal/qwen.py
giotto_llm/online_fine_tuning/__init__.py
giotto_llm/online_fine_tuning/__main__.py
giotto_llm/online_fine_tuning/args.py
giotto_llm/online_fine_tuning/paralel_online_finetuning.py
giotto_llm/online_fine_tuning/utils.py
giotto_llm/parallelize/__init__.py
giotto_llm/parallelize/validation.py
giotto_llm/plot/__init__.py
giotto_llm/plot/matplotlib_plots.py
giotto_llm/prompts/__init__.py
giotto_llm/prompts/consts.py
giotto_llm/prompts/grid_formatter.py
giotto_llm/prompts/text_prompts.py
giotto_llm/reader.py
giotto_llm/tests/.!17051!test.parquet
giotto_llm/tests/conftest.py
giotto_llm/tests/llama_tokenizer/special_tokens_map.json
giotto_llm/tests/llama_tokenizer/tokenizer.json
giotto_llm/tests/llama_tokenizer/tokenizer_config.json
giotto_llm/tests/test.parquet
giotto_llm/tests/test_data.py
giotto_llm/tests/test_grid_formatter.py
giotto_llm/tests/test_reader.py
giotto_llm/tests/test_text_prompts.py
giotto_llm/tests/test_transforms.py
giotto_llm/tests/test_utils.py
giotto_llm/tests/test_wrapped_models.py
giotto_llm/transforms.py
giotto_llm/type_aliases.py
giotto_llm/utils.py
giotto_llm/validation/__init__.py
giotto_llm/validation/__main__.py
giotto_llm/validation/args.py
giotto_llm-0.0.1.dist-info/LICENSE
giotto_llm-0.0.1.dist-info/METADATA
giotto_llm-0.0.1.dist-info/WHEEL
giotto_llm-0.0.1.dist-info/RECORD
