Metadata-Version: 2.1
Name: giotto_llm
Version: 0.0.1
Summary: Wrapper of many OS libraries to finetune LLMs and run them in inference mode efficiently.
Author: Gabriele Beltramo
Author-email: g.beltramo@giotto.ai
Requires-Python: >=3.10,<4.0
Classifier: Programming Language :: Python :: 3
Classifier: Programming Language :: Python :: 3.10
Classifier: Programming Language :: Python :: 3.11
Classifier: Programming Language :: Python :: 3.12
Requires-Dist: gputil (>=1.4.0,<2.0.0)
Requires-Dist: huggingface-hub (>=0.23.4,<0.24.0)
Requires-Dist: json-fix (>=1.0.0,<1.1.0)
Requires-Dist: matplotlib (>=3.7.5,<4.0.0)
Requires-Dist: numpy (==1.26.4)
Requires-Dist: numpydoc (>=1.8.0,<1.9.0)
Requires-Dist: optimum (>1.20.0)
Requires-Dist: poetry (>=1.8.3,<1.9.0)
Requires-Dist: psutil (>=5.9.3,<5.10.0)
Requires-Dist: pydantic (>=2.9.2,<3.0.0)
Requires-Dist: scikit-learn (>=1.3.2,<1.4.0)
Requires-Dist: scipy (>=1.14.1,<2.0.0)
Requires-Dist: sentencepiece (>=0.2.0,<0.3.0)
Requires-Dist: sphinx (>=8.1.3,<8.2.0)
Requires-Dist: sphinx-rtd-theme (>=3.0.2,<3.1.0)
Requires-Dist: torch (>=2.4.0,<2.5.0)
Requires-Dist: transformers (>=4.45.1,<5.0.0)
